nbtlib/__init__.py
nbtlib/__main__.py
nbtlib/cli.py
nbtlib/contrib/__init__.py
nbtlib/contrib/minecraft/__init__.py
nbtlib/contrib/minecraft/structure.py
nbtlib/literal/__init__.py
nbtlib/literal/parser.py
nbtlib/literal/serializer.py
nbtlib/nbt.py
nbtlib/path.py
nbtlib/schema.py
nbtlib/tag.py
nbtlib-2.0.3.dist-info/entry_points.txt
nbtlib-2.0.3.dist-info/LICENSE
nbtlib-2.0.3.dist-info/WHEEL
nbtlib-2.0.3.dist-info/METADATA
nbtlib-2.0.3.dist-info/RECORD
