Metadata-Version: 2.1
Name: nbtlib
Version: 2.0.3
Summary: A python package to read and edit nbt data
Home-page: https://github.com/vberlier/nbtlib
License: MIT
Keywords: nbt,nbt-parser,schema,minecraft,nbtlib
Author: Valentin Berlier
Author-email: berlier.v@gmail.com
Requires-Python: >=3.8,<4.0
Classifier: License :: OSI Approved :: MIT License
Classifier: Programming Language :: Python :: 3
Classifier: Programming Language :: Python :: 3.8
Classifier: Programming Language :: Python :: 3.9
Requires-Dist: numpy
Project-URL: Documentation, https://github.com/vberlier/nbtlib
Project-URL: Repository, https://github.com/vberlier/nbtlib
